gitman/__init__.py
gitman/__main__.py
gitman/cli.py
gitman/commands.py
gitman/common.py
gitman/decorators.py
gitman/exceptions.py
gitman/git.py
gitman/hook-gitman.py
gitman/models/__init__.py
gitman/models/config.py
gitman/models/group.py
gitman/models/source.py
gitman/plugin.py
gitman/settings.py
gitman/shell.py
gitman/tests/__init__.py
gitman/tests/conftest.py
gitman/tests/files/gdm-custom.yml
gitman/tests/files/gdm-default.yml
gitman/tests/files/gitman.yml
gitman/tests/files/subdir/gitman.yml
gitman/tests/files/subdir/subsubdir/gitman.yml
gitman/tests/files/subdir/subsubdir/skip/subsubsubsubdir/gitman.yml
gitman/tests/test_cli.py
gitman/tests/test_commands.py
gitman/tests/test_common.py
gitman/tests/test_git.py
gitman/tests/test_models_config.py
gitman/tests/test_models_group.py
gitman/tests/test_models_source.py
gitman/tests/test_plugin.py
gitman/tests/test_shell.py
gitman/tests/utils.py
gitman-3.7.dist-info/LICENSE.md
gitman-3.7.dist-info/METADATA
gitman-3.7.dist-info/WHEEL
gitman-3.7.dist-info/entry_points.txt
gitman-3.7.dist-info/RECORD
