Metadata-Version: 2.3
Name: gitman
Version: 3.7
Summary: A language-agnostic dependency manager using Git.
License: MIT
Keywords: git,version control,build systems,dependency management,submodules
Author: Jace Browning
Author-email: jacebrowning@gmail.com
Requires-Python: >=3.9,<3.15
Classifier: Development Status :: 5 - Production/Stable
Classifier: Environment :: Console
Classifier: Intended Audience :: Developers
Classifier: License :: OSI Approved :: MIT License
Classifier: Natural Language :: English
Classifier: Operating System :: OS Independent
Classifier: Programming Language :: Python
Classifier: Programming Language :: Python :: 3
Classifier: Programming Language :: Python :: 3.9
Classifier: Programming Language :: Python :: 3.10
Classifier: Programming Language :: Python :: 3.11
Classifier: Programming Language :: Python :: 3.12
Classifier: Programming Language :: Python :: 3.13
Classifier: Topic :: Software Development
Classifier: Topic :: Software Development :: Build Tools
Classifier: Topic :: Software Development :: Version Control
Classifier: Topic :: System :: Software Distribution
Requires-Dist: datafiles (>=2.3.1,<3.0.0)
Requires-Dist: minilog (>=2.3.1,<3.0.0)
Requires-Dist: universal-startfile (>=0.2,<0.4)
Project-URL: Documentation, https://gitman.readthedocs.io
Project-URL: Homepage, https://pypi.org/project/gitman
Project-URL: Repository, https://github.com/jacebrowning/gitman
